emailverifysdk/__init__.py
emailverifysdk/emailverifysdk.py
emailverifysdk/exceptions.py
emailverifysdk/responses.py
emailverifysdk-0.1.0.dist-info/LICENSE
emailverifysdk-0.1.0.dist-info/METADATA
emailverifysdk-0.1.0.dist-info/WHEEL
emailverifysdk-0.1.0.dist-info/top_level.txt
emailverifysdk-0.1.0.dist-info/RECORD
