Metadata-Version: 2.1
Name: emailverifysdk
Version: 0.1.0
Summary: EmailVerify.io Python SDK
Author-email: "EmailVerify.io" <support@emailverify.io>
License: MIT License
Project-URL: Homepage, https://app.emailverify.io
Project-URL: Repository, https://github.com/Clustox/emailverify-python
Project-URL: Documentation, https://www.emailverify.io/api/docs
Keywords: email verification,batch verification,emailverify,emailverify.io,email finder
Classifier: Intended Audience :: Developers
Classifier: License :: OSI Approved :: MIT License
Classifier: Operating System :: OS Independent
Classifier: Programming Language :: Python
Classifier: Programming Language :: Python :: 3
Requires-Python: >=3.7
License-File: LICENSE
Requires-Dist: requests>=2.22.0
